<?xml version="1.0" encoding="UTF-8"?>
<con:testCase id="4d9cdc75-2022-424f-90ea-28d9fca68d95" discardOkResults="false" failOnError="true" failTestCaseOnErrors="true" keepSession="false" name="GetFileLayoutByIdNeg" searchProperties="true" timeout="0" xmlns:con="http://eviware.com/soapui/config">
  <con:settings>
    <con:setting id="4d9cdc75-2022-424f-90ea-28d9fca68d95fileName">GetFileLayoutByIdNeg</con:setting>
  </con:settings>
  <con:testStep type="datasource" name="FileOutputSettingsValidation" id="f475f56f-de26-4e65-82e6-180e2e755b47">
    <con:settings/>
    <con:config xsi:type="con:DataSourceStep" xmlns:xsi="http://www.w3.org/2001/XMLSchema-instance">
      <con:dataSource type="File">
        <con:configuration>
          <fileName>${#Project#ProjectPath}/References/FileOutputSettingsValidation.csv</fileName>
          <separator>,</separator>
          <trim>true</trim>
          <charset>Cp1252</charset>
          <quotedValues>false</quotedValues>
        </con:configuration>
      </con:dataSource>
      <con:shared>true</con:shared>
      <con:restartShared>true</con:restartShared>
      <con:property>InvalidaProgramValidation</con:property>
      <con:property>ErrorCode1</con:property>
      <con:property>ErrorCode2</con:property>
      <con:property>InvalidDisplayOrder1</con:property>
      <con:property>ErrorCode3</con:property>
      <con:property>InvalidReferenceName1</con:property>
      <con:property>ErrorCode4</con:property>
      <con:property>InvalidMessagingValidation</con:property>
      <con:property>ErrorCode5</con:property>
      <con:property>InvalidStatus</con:property>
      <con:property>InvalidStatusValidation</con:property>
      <con:property>InvalidGUID</con:property>
      <con:property>Errorcode6</con:property>
      <con:startRow>1</con:startRow>
      <con:endRow/>
      <con:recordsPerIteration>1</con:recordsPerIteration>
      <con:completeLastOperation>true</con:completeLastOperation>
      <con:trimValues>false</con:trimValues>
      <con:entitizeValues>false</con:entitizeValues>
      <con:restartOnRun>true</con:restartOnRun>
      <con:expandProperties>false</con:expandProperties>
    </con:config>
  </con:testStep>
  <con:testStep type="restrequest" name="GetFileLayoutSettingsWithInvalidGUID" id="d6d8508f-8a12-43d5-942e-8c7281b49b49">
    <con:settings/>
    <con:config service="RestAPIs" resourcePath="/api/v1/referencedata/programs/filelayoutsettings/{layoutId}" methodName="GetFileLayoutbyID" xsi:type="con:RestRequestStep" xmlns:xsi="http://www.w3.org/2001/XMLSchema-instance">
      <con:restRequest name="GetFileLayoutSettingsWithInvalidGUID" id="4fea1c15-4a33-4a4e-8ad4-2289f172d125" mediaType="application/json">
        <con:settings>
          <con:setting id="com.eviware.soapui.impl.wsdl.WsdlRequest@request-headers">&lt;xml-fragment/></con:setting>
        </con:settings>
        <con:endpoint>https://d3aldv-pveapi.skynetlowerenv.com/</con:endpoint>
        <con:request/>
        <con:originalUri>https://q3alin-pveapi.skynetlowerenv.com/api/v1/referencedata/programs/filelayoutsettings/</con:originalUri>
        <con:assertion type="DataAndMetadataAssertion" id="241fecc3-1bee-4f37-9ca8-aef41f55a83b" name="Smart Assertion for HTTP status code">
          <con:configuration xsi:type="con:DataAndMetadataAssertion">
            <con:mode>Received Metadata</con:mode>
            <con:elements>
              <con:path>$['Headers']['date']</con:path>
              <con:element>date</con:element>
              <con:operatorId>1</con:operatorId>
              <con:enabled>false</con:enabled>
              <con:expectedValue>Tue, 26 Apr 2022 10:41:11 GMT</con:expectedValue>
              <con:caseSensitive>true</con:caseSensitive>
              <con:numberType>false</con:numberType>
              <con:expectedDataType>1</con:expectedDataType>
            </con:elements>
            <con:elements>
              <con:path>$['Headers']['server']</con:path>
              <con:element>server</con:element>
              <con:operatorId>1</con:operatorId>
              <con:enabled>false</con:enabled>
              <con:expectedValue>Apache/2.4.6 (Red Hat Enterprise Linux) OpenSSL/1.0.2k-fips</con:expectedValue>
              <con:caseSensitive>true</con:caseSensitive>
              <con:numberType>false</con:numberType>
              <con:expectedDataType>1</con:expectedDataType>
            </con:elements>
            <con:elements>
              <con:path>$['Headers']['content-length']</con:path>
              <con:element>content-length</con:element>
              <con:operatorId>1</con:operatorId>
              <con:enabled>false</con:enabled>
              <con:expectedValue>0</con:expectedValue>
              <con:caseSensitive>true</con:caseSensitive>
              <con:numberType>false</con:numberType>
              <con:expectedDataType>1</con:expectedDataType>
            </con:elements>
            <con:elements>
              <con:path>$['Headers']['x-content-type-options']</con:path>
              <con:element>x-content-type-options</con:element>
              <con:operatorId>1</con:operatorId>
              <con:enabled>false</con:enabled>
              <con:expectedValue>nosniff</con:expectedValue>
              <con:caseSensitive>true</con:caseSensitive>
              <con:numberType>false</con:numberType>
              <con:expectedDataType>1</con:expectedDataType>
            </con:elements>
            <con:elements>
              <con:path>$['Headers']['x-xss-protection']</con:path>
              <con:element>x-xss-protection</con:element>
              <con:operatorId>1</con:operatorId>
              <con:enabled>false</con:enabled>
              <con:expectedValue>1</con:expectedValue>
              <con:caseSensitive>true</con:caseSensitive>
              <con:numberType>false</con:numberType>
              <con:expectedDataType>1</con:expectedDataType>
            </con:elements>
            <con:elements>
              <con:path>$['Headers']['x-frame-options']</con:path>
              <con:element>x-frame-options</con:element>
              <con:operatorId>1</con:operatorId>
              <con:enabled>false</con:enabled>
              <con:expectedValue>DENY</con:expectedValue>
              <con:caseSensitive>true</con:caseSensitive>
              <con:numberType>false</con:numberType>
              <con:expectedDataType>1</con:expectedDataType>
            </con:elements>
            <con:elements>
              <con:path>$['Headers']['connection']</con:path>
              <con:element>connection</con:element>
              <con:operatorId>1</con:operatorId>
              <con:enabled>false</con:enabled>
              <con:expectedValue>keep-alive</con:expectedValue>
              <con:caseSensitive>true</con:caseSensitive>
              <con:numberType>false</con:numberType>
              <con:expectedDataType>1</con:expectedDataType>
            </con:elements>
            <con:elements>
              <con:path>$['Headers']['correlationid']</con:path>
              <con:element>correlationid</con:element>
              <con:operatorId>1</con:operatorId>
              <con:enabled>false</con:enabled>
              <con:expectedValue>2b5146da-4be0-4beb-d9e2-4d504f72c8cc</con:expectedValue>
              <con:caseSensitive>true</con:caseSensitive>
              <con:numberType>false</con:numberType>
              <con:expectedDataType>1</con:expectedDataType>
            </con:elements>
            <con:elements>
              <con:path>$['Headers']['process-time']</con:path>
              <con:element>process-time</con:element>
              <con:operatorId>1</con:operatorId>
              <con:enabled>false</con:enabled>
              <con:expectedValue>2ms</con:expectedValue>
              <con:caseSensitive>true</con:caseSensitive>
              <con:numberType>false</con:numberType>
              <con:expectedDataType>1</con:expectedDataType>
            </con:elements>
            <con:elements>
              <con:path>$['Headers']['#status#']</con:path>
              <con:element>#status#</con:element>
              <con:operatorId>1</con:operatorId>
              <con:enabled>true</con:enabled>
              <con:expectedValue>HTTP/1.1 404 Not Found</con:expectedValue>
              <con:caseSensitive>true</con:caseSensitive>
              <con:numberType>false</con:numberType>
              <con:expectedDataType>1</con:expectedDataType>
            </con:elements>
            <con:elements>
              <con:path>$['Headers']['new-correlationid']</con:path>
              <con:element>new-correlationid</con:element>
              <con:operatorId>1</con:operatorId>
              <con:enabled>false</con:enabled>
              <con:expectedValue>0HMH712EJGC4R:0000006E</con:expectedValue>
              <con:caseSensitive>true</con:caseSensitive>
              <con:numberType>false</con:numberType>
              <con:expectedDataType>1</con:expectedDataType>
            </con:elements>
            <con:originalMessage>{"Headers":{"date":"Tue, 26 Apr 2022 10:41:11 GMT","server":"Apache/2.4.6 (Red Hat Enterprise Linux) OpenSSL/1.0.2k-fips","content-length":"0","x-content-type-options":"nosniff","x-xss-protection":"1","x-frame-options":"DENY","connection":"keep-alive","correlationid":"2b5146da-4be0-4beb-d9e2-4d504f72c8cc","process-time":"2ms","#status#":"HTTP/1.1 404 Not Found","new-correlationid":"0HMH712EJGC4R:0000006E"}}</con:originalMessage>
          </con:configuration>
        </con:assertion>
        <con:credentials>
          <con:selectedAuthProfile>No Authorization</con:selectedAuthProfile>
          <con:authType>No Authorization</con:authType>
        </con:credentials>
        <con:jmsConfig JMSDeliveryMode="PERSISTENT"/>
        <con:parameters>
          <con:entry key="layoutId" value="${FileOutputSettingsValidation#InvalidGUID}"/>
        </con:parameters>
      </con:restRequest>
    </con:config>
  </con:testStep>
  <con:properties/>
  <con:reportParameters/>
</con:testCase>
